{"BlockIO":"111kB / 6.97MB","CPUPerc":"74.15%","Container":"apache-prefork","ID":"1647dfe2e4a5","MemPerc":"0.15%","MemUsage":"48.06MiB / 31.26GiB","Name":"apache-prefork","NetIO":"229MB / 24.2GB","PIDs":"148"}
{"BlockIO":"111kB / 6.97MB","CPUPerc":"337.87%","Container":"apache-prefork","ID":"1647dfe2e4a5","MemPerc":"0.15%","MemUsage":"49.59MiB / 31.26GiB","Name":"apache-prefork","NetIO":"246MB / 25.6GB","PIDs":"150"}
{"BlockIO":"111kB / 6.97MB","CPUPerc":"381.16%","Container":"apache-prefork","ID":"1647dfe2e4a5","MemPerc":"0.16%","MemUsage":"50.22MiB / 31.26GiB","Name":"apache-prefork","NetIO":"264MB / 27.3GB","PIDs":"151"}
{"BlockIO":"111kB / 6.97MB","CPUPerc":"391.84%","Container":"apache-prefork","ID":"1647dfe2e4a5","MemPerc":"0.15%","MemUsage":"49.09MiB / 31.26GiB","Name":"apache-prefork","NetIO":"281MB / 29GB","PIDs":"151"}
{"BlockIO":"111kB / 6.97MB","CPUPerc":"404.13%","Container":"apache-prefork","ID":"1647dfe2e4a5","MemPerc":"0.15%","MemUsage":"49.38MiB / 31.26GiB","Name":"apache-prefork","NetIO":"297MB / 30.7GB","PIDs":"151"}
{"BlockIO":"111kB / 6.97MB","CPUPerc":"171.69%","Container":"apache-prefork","ID":"1647dfe2e4a5","MemPerc":"0.15%","MemUsage":"48.69MiB / 31.26GiB","Name":"apache-prefork","NetIO":"309MB / 31.9GB","PIDs":"151"}
{"BlockIO":"111kB / 6.97MB","CPUPerc":"0.00%","Container":"apache-prefork","ID":"1647dfe2e4a5","MemPerc":"0.15%","MemUsage":"48.66MiB / 31.26GiB","Name":"apache-prefork","NetIO":"309MB / 31.9GB","PIDs":"151"}
{"BlockIO":"111kB / 6.97MB","CPUPerc":"0.00%","Container":"apache-prefork","ID":"1647dfe2e4a5","MemPerc":"0.15%","MemUsage":"48.66MiB / 31.26GiB","Name":"apache-prefork","NetIO":"309MB / 31.9GB","PIDs":"151"}
{"BlockIO":"111kB / 6.97MB","CPUPerc":"0.00%","Container":"apache-prefork","ID":"1647dfe2e4a5","MemPerc":"0.15%","MemUsage":"48.66MiB / 31.26GiB","Name":"apache-prefork","NetIO":"310MB / 31.9GB","PIDs":"151"}
{"BlockIO":"111kB / 6.97MB","CPUPerc":"0.00%","Container":"apache-prefork","ID":"1647dfe2e4a5","MemPerc":"0.15%","MemUsage":"48.64MiB / 31.26GiB","Name":"apache-prefork","NetIO":"311MB / 31.9GB","PIDs":"151"}
{"BlockIO":"111kB / 6.97MB","CPUPerc":"4.26%","Container":"apache-prefork","ID":"1647dfe2e4a5","MemPerc":"0.15%","MemUsage":"48.65MiB / 31.26GiB","Name":"apache-prefork","NetIO":"311MB / 31.9GB","PIDs":"151"}
{"BlockIO":"111kB / 6.97MB","CPUPerc":"0.00%","Container":"apache-prefork","ID":"1647dfe2e4a5","MemPerc":"0.15%","MemUsage":"48.63MiB / 31.26GiB","Name":"apache-prefork","NetIO":"311MB / 31.9GB","PIDs":"151"}
{"BlockIO":"111kB / 6.97MB","CPUPerc":"0.01%","Container":"apache-prefork","ID":"1647dfe2e4a5","MemPerc":"0.15%","MemUsage":"48.63MiB / 31.26GiB","Name":"apache-prefork","NetIO":"311MB / 31.9GB","PIDs":"151"}
{"BlockIO":"111kB / 6.97MB","CPUPerc":"0.00%","Container":"apache-prefork","ID":"1647dfe2e4a5","MemPerc":"0.15%","MemUsage":"48.64MiB / 31.26GiB","Name":"apache-prefork","NetIO":"311MB / 31.9GB","PIDs":"151"}
{"BlockIO":"111kB / 9.16MB","CPUPerc":"0.00%","Container":"apache-prefork","ID":"1647dfe2e4a5","MemPerc":"0.15%","MemUsage":"48.64MiB / 31.26GiB","Name":"apache-prefork","NetIO":"311MB / 31.9GB","PIDs":"151"}
{"BlockIO":"111kB / 9.17MB","CPUPerc":"4.40%","Container":"apache-prefork","ID":"1647dfe2e4a5","MemPerc":"0.15%","MemUsage":"48.64MiB / 31.26GiB","Name":"apache-prefork","NetIO":"312MB / 31.9GB","PIDs":"151"}
{"BlockIO":"111kB / 9.17MB","CPUPerc":"0.00%","Container":"apache-prefork","ID":"1647dfe2e4a5","MemPerc":"0.15%","MemUsage":"48.64MiB / 31.26GiB","Name":"apache-prefork","NetIO":"312MB / 31.9GB","PIDs":"151"}
{"BlockIO":"111kB / 9.17MB","CPUPerc":"0.01%","Container":"apache-prefork","ID":"1647dfe2e4a5","MemPerc":"0.15%","MemUsage":"48.64MiB / 31.26GiB","Name":"apache-prefork","NetIO":"312MB / 31.9GB","PIDs":"151"}
{"BlockIO":"111kB / 9.17MB","CPUPerc":"0.00%","Container":"apache-prefork","ID":"1647dfe2e4a5","MemPerc":"0.15%","MemUsage":"48.64MiB / 31.26GiB","Name":"apache-prefork","NetIO":"312MB / 31.9GB","PIDs":"151"}
{"BlockIO":"111kB / 9.17MB","CPUPerc":"0.00%","Container":"apache-prefork","ID":"1647dfe2e4a5","MemPerc":"0.15%","MemUsage":"48.64MiB / 31.26GiB","Name":"apache-prefork","NetIO":"312MB / 31.9GB","PIDs":"151"}
{"BlockIO":"111kB / 9.17MB","CPUPerc":"10.04%","Container":"apache-prefork","ID":"1647dfe2e4a5","MemPerc":"0.15%","MemUsage":"48.65MiB / 31.26GiB","Name":"apache-prefork","NetIO":"313MB / 31.9GB","PIDs":"151"}
